{
  "tasks": [
    {
      "id": "1",
      "taskStart": "Fri Apr 26 2024 06:42:46 GMT+0300 (EEST)",
      "taskEnd": "Fri Apr 26 2024 06:42:49 GMT+0300 (EEST)",
      "duration": 2717
    },
    {
      "id": "2",
      "taskStart": "Thu Apr 25 2024 00:00:00 GMT+0300 (EEST)",
      "taskEnd": "Thu Apr 25 2024 00:00:00 GMT+0300 (EEST)",
      "duration": 2334
    },
    {
      "id": "75b7",
      "taskStart": "2024-04-28T18:17:03.058Z",
      "taskEnd": "2024-04-28T18:17:03.834Z",
      "duration": 776
    }
  ]
}